carte_ai/__init__.py
carte_ai/configs/__init__.py
carte_ai/configs/carte_configs.py
carte_ai/configs/directory.py
carte_ai/configs/model_parameters.py
carte_ai/configs/visuailization.py
carte_ai/data/__init__.py
carte_ai/data/config_wine_dot_com_prices.json
carte_ai/data/config_wine_pl.json
carte_ai/data/config_wine_vivino_price.json
carte_ai/data/load_data.py
carte_ai/data/spotify.parquet
carte_ai/data/wine_dot_com_prices.parquet
carte_ai/data/wine_pl.parquet
carte_ai/data/wine_vivino_price.parquet
carte_ai/data/etc/kg_pretrained.pt
carte_ai/scripts/__init__.py
carte_ai/scripts/compile_results_singletable.py
carte_ai/scripts/download_data.py
carte_ai/scripts/evaluate_singletable.py
carte_ai/scripts/preprocess_lm.py
carte_ai/scripts/preprocess_raw.py
carte_ai/src/__init__.py
carte_ai/src/baseline_multitable.py
carte_ai/src/baseline_singletable_nn.py
carte_ai/src/carte_estimator.py
carte_ai/src/carte_gridsearch.py
carte_ai/src/carte_model.py
carte_ai/src/carte_table_to_graph copy.py
carte_ai/src/carte_table_to_graph.py
carte_ai/src/carte_table_to_graph_1.py
carte_ai/src/carte_table_to_graph_2.py
carte_ai/src/carte_table_to_graph_3.py
carte_ai/src/carte_table_to_graph_good.py
carte_ai/src/carte_table_to_graph_old.py
carte_ai/src/evaluate_utils.py
carte_ai/src/preprocess_utils.py
carte_ai/src/visualization_utils.py
carte_ai-0.0.26.dist-info/LICENSE.txt
carte_ai-0.0.26.dist-info/METADATA
carte_ai-0.0.26.dist-info/WHEEL
carte_ai-0.0.26.dist-info/top_level.txt
carte_ai-0.0.26.dist-info/RECORD
