Metadata-Version: 2.2
Name: carte-ai
Version: 0.0.26
Summary: CARTE-AI: Context Aware Representation of Table Entries for AI
Author: Léo Grinsztajn, Gaël Varoquaux
Author-email: Myung Jun Kim <test@gmail.com>
License: MIT license
Project-URL: Homepage, https://github.com/soda-inria/carte
Keywords: carte-ai
Classifier: Development Status :: 2 - Pre-Alpha
Classifier: Intended Audience :: Developers
Classifier: License :: OSI Approved :: MIT License
Classifier: Environment :: Console
Classifier: Operating System :: OS Independent
Classifier: Operating System :: POSIX :: Linux
Classifier: Operating System :: MacOS
Classifier: Operating System :: POSIX
Classifier: Operating System :: Microsoft :: Windows
Classifier: Natural Language :: English
Classifier: Programming Language :: Python :: 3.10
Classifier: Programming Language :: Python :: 3.11
Classifier: Programming Language :: Python :: 3.12
Requires-Python: >=3.10.12
License-File: LICENSE.txt
Requires-Dist: numpy
Requires-Dist: pandas
Requires-Dist: scipy
Requires-Dist: scikit-learn
Requires-Dist: torch
Requires-Dist: torch-geometric
Requires-Dist: torcheval
Requires-Dist: fasttext
Requires-Dist: category-encoders
Requires-Dist: tabpfn
Requires-Dist: xgboost
Requires-Dist: catboost
Requires-Dist: seaborn
Requires-Dist: pyarrow
Provides-Extra: test
Requires-Dist: pytest; extra == "test"
Requires-Dist: coverage; extra == "test"
